nempy/__init__.py
nempy/markets.py
nempy/time_sequential.py
nempy/help_functions/__init__.py
nempy/help_functions/helper_functions.py
nempy/historical_inputs/__init__.py
nempy/historical_inputs/aemo_to_nempy_name_mapping.py
nempy/historical_inputs/constraints.py
nempy/historical_inputs/demand.py
nempy/historical_inputs/interconnectors.py
nempy/historical_inputs/loaders.py
nempy/historical_inputs/mms_db.py
nempy/historical_inputs/rhs_calculator.py
nempy/historical_inputs/units.py
nempy/historical_inputs/xml_cache.py
nempy/spot_market_backend/__init__.py
nempy/spot_market_backend/check.py
nempy/spot_market_backend/dataframe_validator.py
nempy/spot_market_backend/elastic_constraints.py
nempy/spot_market_backend/fcas_constraints.py
nempy/spot_market_backend/interconnectors.py
nempy/spot_market_backend/market_constraints.py
nempy/spot_market_backend/objective_function.py
nempy/spot_market_backend/ramp_rate_processing.py
nempy/spot_market_backend/solver_interface.py
nempy/spot_market_backend/unit_constraints.py
nempy/spot_market_backend/variable_ids.py
nempy-3.0.3.dist-info/LICENSE
nempy-3.0.3.dist-info/METADATA
nempy-3.0.3.dist-info/WHEEL
nempy-3.0.3.dist-info/top_level.txt
nempy-3.0.3.dist-info/RECORD
