Metadata-Version: 2.2
Name: nempy
Version: 3.0.3
Summary: A flexible tool kit for modelling Australia's National Electricity Market dispatch procedure.
Author-email: nick-gorman <n.gorman305@gmail.com>
Requires-Python: >=3.9
License-File: LICENSE
Requires-Dist: mip==1.16rc0
Requires-Dist: pandas>=2.2.2
Requires-Dist: xmltodict==0.12.0
Requires-Dist: requests>=2.0.0
